.VERSION
AUTHORS.rst
CONTRIBUTING.rst
HISTORY.rst
LICENSE
MANIFEST.in
Pipfile
Pipfile.lock
README.rst
dev-requirements.txt
requirements.txt
setup.cfg
setup.py
awsapilib/.VERSION
awsapilib/AUTHORS.rst
awsapilib/CONTRIBUTING.rst
awsapilib/HISTORY.rst
awsapilib/LICENSE
awsapilib/Pipfile
awsapilib/Pipfile.lock
awsapilib/README.rst
awsapilib/USAGE_BILLING.rst
awsapilib/USAGE_CONTROL_TOWER.rst
awsapilib/USAGE_SSO.rst
awsapilib/__init__.py
awsapilib/_version.py
awsapilib/awsapilib.py
awsapilib/awsapilibexceptions.py
awsapilib/dev-requirements.txt
awsapilib/requirements.txt
awsapilib.egg-info/PKG-INFO
awsapilib.egg-info/SOURCES.txt
awsapilib.egg-info/dependency_links.txt
awsapilib.egg-info/not-zip-safe
awsapilib.egg-info/requires.txt
awsapilib.egg-info/top_level.txt
awsapilib/__pycache__/__init__.cpython-37.pyc
awsapilib/__pycache__/__init__.cpython-39.pyc
awsapilib/__pycache__/_version.cpython-37.pyc
awsapilib/__pycache__/_version.cpython-39.pyc
awsapilib/__pycache__/awsapilib.cpython-39.pyc
awsapilib/__pycache__/awsapilibexceptions.cpython-39.pyc
awsapilib/authentication/__init__.py
awsapilib/authentication/authentication.py
awsapilib/authentication/authenticationexceptions.py
awsapilib/authentication/utils.py
awsapilib/authentication/__pycache__/__init__.cpython-37.pyc
awsapilib/authentication/__pycache__/__init__.cpython-39.pyc
awsapilib/authentication/__pycache__/authentication.cpython-37.pyc
awsapilib/authentication/__pycache__/authentication.cpython-39.pyc
awsapilib/authentication/__pycache__/authenticationexceptions.cpython-37.pyc
awsapilib/authentication/__pycache__/authenticationexceptions.cpython-39.pyc
awsapilib/authentication/__pycache__/metadata.cpython-39.pyc
awsapilib/authentication/__pycache__/utils.cpython-37.pyc
awsapilib/authentication/__pycache__/utils.cpython-39.pyc
awsapilib/billing/__init__.py
awsapilib/billing/billing.py
awsapilib/billing/billingexceptions.py
awsapilib/billing/__pycache__/__init__.cpython-37.pyc
awsapilib/billing/__pycache__/__init__.cpython-39.pyc
awsapilib/billing/__pycache__/billing.cpython-37.pyc
awsapilib/billing/__pycache__/billing.cpython-39.pyc
awsapilib/billing/__pycache__/billingexceptions.cpython-37.pyc
